[
   {
      "ScholarshipName": "",
      "ScholarshipReqs": [
         "Have a 4.0",
         "Write Essay",
         "Get Letter of Recommendation"
      ],
      "ScholarLink": "",
      "ScholarStatus": "",
      "Amount": {
        "FreqYear": "3",
        "AmountPerF": "3000"

      },
      "postNumber": "1"
   },
   {
      "ScholarshipName": "",
      "ScholarshipReqs": [
         "Get Letter of Recommendation",
         "Get Letter of Recommendation",
         "Update Resume"
      ],
      "ScholarLink": "",
      "ScholarStatus": "",
      "Amount": {
         "FreqYear": "3",
         "AmountPerF": "3000"
      },
      "postNumber": "2"
   },
   {
      "ScholarshipName": "",
      "ScholarshipReqs": [
         "Have a 4.0",
         "Have a 4.0",
         "Have a 4.0",
         "Have a 4.0"
      ],
      "ScholarLink": "",
      "ScholarStatus": "",
      "Amount": {
         "FreqYear": "3",
         "AmountPerF": "3000"
      },
      "postNumber": "3"
   },
   {
      "ScholarshipName": "",
      "ScholarshipReqs": [
         "Have a 3.8 average",
         "Write application essay",
         "Do Project"
      ],
      "ScholarLink": "",
      "ScholarStatus": "",
      "Amount": {
         "FreqYear": "3",
         "AmountPerF": "3000"
      },
      "postNumber": "4"
   }
]